pytest_inmanta_srlinux/__init__.py
pytest_inmanta_srlinux/device.py
pytest_inmanta_srlinux/get_config.py
pytest_inmanta_srlinux/namespaces.py
pytest_inmanta_srlinux/plugin.py
pytest_inmanta_srlinux/py.typed
pytest_inmanta_srlinux/models/basic.cf
pytest_inmanta_srlinux/models/ip_interface.cf
pytest_inmanta_srlinux-0.1.0.dist-info/licenses/LICENSE.txt
pytest_inmanta_srlinux-0.1.0.dist-info/METADATA
pytest_inmanta_srlinux-0.1.0.dist-info/WHEEL
pytest_inmanta_srlinux-0.1.0.dist-info/entry_points.txt
pytest_inmanta_srlinux-0.1.0.dist-info/top_level.txt
pytest_inmanta_srlinux-0.1.0.dist-info/RECORD
