Metadata-Version: 2.4
Name: pytest-inmanta-srlinux
Version: 0.1.0
Summary: Pytest library to facilitate end to end testing of inmanta projects
Author-email: Inmanta <code@inmanta.com>
License:                                  Apache License
Project-URL: Homepage, https://inmanta.com
Project-URL: Bug Reports, https://code.inmanta.com/solutions/tools/pytest-inmanta-srlinux/-/issues
Project-URL: Source, https://code.inmanta.com/solutions/tools/pytest-inmanta-srlinux/
Keywords: pytest,inmanta,srlinux,cpe
Classifier: Development Status :: 3 - Alpha
Classifier: Intended Audience :: Developers
Classifier: Programming Language :: Python :: 3
Classifier: Programming Language :: Python :: 3.9
Classifier: Programming Language :: Python :: 3.10
Classifier: Programming Language :: Python :: 3.11
Classifier: Programming Language :: Python :: 3.12
Classifier: Programming Language :: Python :: 3.13
Classifier: Programming Language :: Python :: 3 :: Only
Requires-Python: >=3.9
License-File: LICENSE.txt
Requires-Dist: paramiko
Requires-Dist: pingparsing
Requires-Dist: pytest-inmanta
Requires-Dist: inmanta-module-yang
Requires-Dist: inmanta-module-nokia-srlinux
Requires-Dist: inmanta-module-std>=8.1.0.dev0
Requires-Dist: pygnmi
Dynamic: license-file
